superqode/__init__.py
superqode/acp_discovery.py
superqode/agent_output.py
superqode/agent_stream.py
superqode/app_enhanced.py
superqode/app_main.py
superqode/approval.py
superqode/atomic.py
superqode/danger.py
superqode/design_system.py
superqode/diff_view.py
superqode/enterprise.py
superqode/file_explorer.py
superqode/file_viewer.py
superqode/flash.py
superqode/history.py
superqode/main.py
superqode/notifications.py
superqode/plan.py
superqode/pure_mode.py
superqode/session.py
superqode/sidebar.py
superqode/stream_view.py
superqode/superqe_cli.py
superqode/tool_call.py
superqode/tui.py
superqode/tui_integration.py
superqode/undo_manager.py
superqode/acp/__init__.py
superqode/acp/client.py
superqode/acp/permission_screen.py
superqode/acp/types.py
superqode/agent/__init__.py
superqode/agent/edit_strategies.py
superqode/agent/loop.py
superqode/agent/qe_report_templates.py
superqode/agent/system_prompts.py
superqode/agents/__init__.py
superqode/agents/acp_registry.py
superqode/agents/client.py
superqode/agents/discovery.py
superqode/agents/messaging.py
superqode/agents/persona.py
superqode/agents/registry.py
superqode/agents/schema.py
superqode/agents/unified.py
superqode/agents/data/ampcode.com.toml
superqode/agents/data/augmentcode.com.toml
superqode/agents/data/cagent.dev.toml
superqode/agents/data/claude.com.toml
superqode/agents/data/codeassistant.dev.toml
superqode/agents/data/codex.openai.com.toml
superqode/agents/data/fastagent.ai.toml
superqode/agents/data/geminicli.com.toml
superqode/agents/data/goose.block.xyz.toml
superqode/agents/data/junie.jetbrains.com.toml
superqode/agents/data/kimi.moonshot.cn.toml
superqode/agents/data/llmlingagent.dev.toml
superqode/agents/data/molt.bot.toml
superqode/agents/data/opencode.ai.toml
superqode/agents/data/stakpak.dev.toml
superqode/agents/data/vtcode.dev.toml
superqode/app/__init__.py
superqode/app/constants.py
superqode/app/css.py
superqode/app/models.py
superqode/app/suggester.py
superqode/app/widgets.py
superqode-0.1.9.dist-info/licenses/LICENSE
superqode-0.1.9.dist-info/METADATA
superqode-0.1.9.dist-info/WHEEL
superqode-0.1.9.dist-info/entry_points.txt
superqode-0.1.9.dist-info/top_level.txt
superqode-0.1.9.dist-info/RECORD
