Metadata-Version: 2.4
Name: superqode
Version: 0.1.9
Summary: SuperQode: Super Quality Engineering for Agentic Coding Teams
Author-email: Shashi Jagtap <info@super-agentic.ai>
Maintainer-email: Shashi Jagtap <info@super-agentic.ai>
Project-URL: Repository, https://github.com/SuperagenticAI/superqode
Project-URL: Documentation, https://superagenticai.github.io/superqode/
Project-URL: Issues, https://github.com/SuperagenticAI/superqode/issues
Project-URL: Changelog, https://github.com/SuperagenticAI/superqode/blob/main/CHANGELOG.md
Keywords: ai,coding-agents,multi-agent,orchestration,sdlc,automation,mcp,kubernetes,superqode
Classifier: Development Status :: 3 - Alpha
Classifier: Intended Audience :: Developers
Classifier: License :: OSI Approved :: GNU Affero General Public License v3
Classifier: Programming Language :: Python :: 3
Classifier: Programming Language :: Python :: 3.12
Classifier: Topic :: Software Development :: Libraries :: Python Modules
Classifier: Topic :: Software Development :: Quality Assurance
Classifier: Topic :: Software Development :: Build Tools
Requires-Python: >=3.12
License-File: LICENSE
Requires-Dist: pyyaml>=6.0
Requires-Dist: click>=8.0.0
Requires-Dist: litellm>=1.80.11
Requires-Dist: agent-client-protocol>=0.7.0
Requires-Dist: prompt_toolkit>=3.0.0
Requires-Dist: rich>=13.0.0
Requires-Dist: textual>=0.47.0
Requires-Dist: mcp>=1.25.0
Requires-Dist: anyio>=4.0.0
Requires-Dist: httpx>=0.24.0
Requires-Dist: httpx-sse>=0.4.0
Requires-Dist: codeoptix>=0.1.0
Requires-Dist: superopt>=0.1.1
Provides-Extra: mlx
Requires-Dist: mlx-lm<0.30.0,>=0.28.3; python_version < "3.14" and extra == "mlx"
Provides-Extra: dev
Requires-Dist: pytest>=7.0.0; extra == "dev"
Requires-Dist: pytest-asyncio>=0.21.0; extra == "dev"
Requires-Dist: pytest-cov>=4.0.0; extra == "dev"
Requires-Dist: coverage>=7.0.0; extra == "dev"
Requires-Dist: ruff>=0.1.0; extra == "dev"
Requires-Dist: mypy>=1.0.0; extra == "dev"
Requires-Dist: pre-commit>=3.0.0; extra == "dev"
Provides-Extra: testing
Requires-Dist: pytest>=7.0.0; extra == "testing"
Requires-Dist: pytest-asyncio>=0.21.0; extra == "testing"
Requires-Dist: pytest-cov>=4.0.0; extra == "testing"
Requires-Dist: coverage>=7.0.0; extra == "testing"
Requires-Dist: bandit>=1.7.0; extra == "testing"
Requires-Dist: httpx>=0.24.0; extra == "testing"
Provides-Extra: linters
Requires-Dist: bandit>=1.7.5; extra == "linters"
Requires-Dist: pylint>=3.0.0; extra == "linters"
Requires-Dist: flake8>=6.1.0; extra == "linters"
Requires-Dist: safety>=2.3.0; extra == "linters"
Requires-Dist: pip-audit>=2.6.0; extra == "linters"
Provides-Extra: ui-testing
Requires-Dist: selenium>=4.0.0; extra == "ui-testing"
Requires-Dist: playwright>=1.0.0; extra == "ui-testing"
Provides-Extra: performance
Requires-Dist: locust>=2.0.0; extra == "performance"
Provides-Extra: docs
Requires-Dist: mkdocs>=1.5.0; extra == "docs"
Requires-Dist: mkdocs-material>=9.4.0; extra == "docs"
Requires-Dist: pymdown-extensions>=10.0.0; extra == "docs"
Requires-Dist: mkdocs-minify-plugin>=0.7.0; extra == "docs"
Dynamic: license-file
